Fastpix/__init__.py
Fastpix/_version.py
Fastpix/basesdk.py
Fastpix/dimensions.py
Fastpix/drm_configurations.py
Fastpix/errors.py
Fastpix/httpclient.py
Fastpix/in_video_ai_features.py
Fastpix/input_video.py
Fastpix/live_playback.py
Fastpix/manage_live_stream.py
Fastpix/manage_videos.py
Fastpix/metrics.py
Fastpix/playback.py
Fastpix/playlist.py
Fastpix/py.typed
Fastpix/sdk.py
Fastpix/sdkconfiguration.py
Fastpix/signing_keys.py
Fastpix/simulcast_stream.py
Fastpix/start_live_stream.py
Fastpix/views_sdk.py
Fastpix/_hooks/__init__.py
Fastpix/_hooks/sdkhooks.py
Fastpix/_hooks/types.py
Fastpix/errors/__init__.py
Fastpix/errors/badrequest_error.py
Fastpix/errors/duplicatemp4support_error.py
Fastpix/errors/duplicatereferenceiderrorresponse.py
Fastpix/errors/enable_live_streamop.py
Fastpix/errors/fastpixdefaulterror.py
Fastpix/errors/fastpixerror.py
Fastpix/errors/forbidden_error.py
Fastpix/errors/forbiddenresponse_error.py
Fastpix/errors/invalidpermission_error.py
Fastpix/errors/invalidplaylistidresponse_error.py
Fastpix/errors/livenotfounderror.py
Fastpix/errors/mediaclipnotfound_error.py
Fastpix/errors/medianotfound_error.py
Fastpix/errors/mediaorplaybacknotfound_error.py
Fastpix/errors/no_response_error.py
Fastpix/errors/notfounderror.py
Fastpix/errors/notfounderrorplaybackid.py
Fastpix/errors/notfounderrorsimulcast.py
Fastpix/errors/responsevalidationerror.py
Fastpix/errors/signingkeynotfounderror.py
Fastpix/errors/simulcastunavailable_error.py
Fastpix/errors/streamalreadydisablederror.py
Fastpix/errors/streamalreadyenablederror.py
Fastpix/errors/trackduplicaterequest_error.py
Fastpix/errors/trialplanrestrictionerror.py
Fastpix/errors/unauthorized_error.py
Fastpix/errors/unauthorizedresponse_error.py
Fastpix/errors/validationerrorresponse.py
Fastpix/errors/viewnotfound_error.py
Fastpix/models/__init__.py
Fastpix/models/accesspolicy.py
Fastpix/models/add_media_to_playlistop.py
Fastpix/models/add_media_trackop.py
Fastpix/models/addtrackrequest.py
fastpix_python-1.0.0.dist-info/licenses/LICENSE
fastpix_python-1.0.0.dist-info/METADATA
fastpix_python-1.0.0.dist-info/WHEEL
fastpix_python-1.0.0.dist-info/top_level.txt
fastpix_python-1.0.0.dist-info/RECORD
