Metadata-Version: 2.4
Name: fastpix_python
Version: 1.0.0
Summary: Python Client SDK Generated by fastpix.
Home-page: https://github.com/FastPix/fastpix-python
Author: fastpix
Author-email: dev@fastpix.io
Requires-Python: >=3.7
License-File: LICENSE
Requires-Dist: httpcore>=1.0.9
Requires-Dist: httpx>=0.28.1
Requires-Dist: pydantic>=2.11.2
Dynamic: author-email
Dynamic: home-page
Dynamic: license-file
Dynamic: requires-python
